LICENSE
MANIFEST.in
README.rst
setup.py
django_logging/__init__.py
django_logging/apps.py
django_logging/cursor_wrapper.py
django_logging/handlers.py
django_logging/log_object.py
django_logging/logger.py
django_logging/middleware.py
django_logging/settings.py
django_logging_json_fork.egg-info/PKG-INFO
django_logging_json_fork.egg-info/SOURCES.txt
django_logging_json_fork.egg-info/dependency_links.txt
django_logging_json_fork.egg-info/requires.txt
django_logging_json_fork.egg-info/top_level.txt